fluidtools.cpython-38-darwin.so
fluidtools-0.2.0.dist-info/METADATA
fluidtools-0.2.0.dist-info/WHEEL
fluidtools-0.2.0.dist-info/top_level.txt
fluidtools-0.2.0.dist-info/RECORD
