Metadata-Version: 2.1
Name: fluidtools
Version: 0.2.0
Summary: Utilities to work with sounfonts
Home-page: https://github.com/gesellkammer/fluidtools
Author: Eduardo Moguillansky
Author-email: eduardo.moguillansky@gmail.com
Maintainer: Eduardo Moguillansky
Maintainer-email: eduardo.moguillansky@gmail.com
License: LGPL
Requires-Python: >=3.8
